rtl/alu.sv
module alu (
    input  logic [31:0] a,      // operand 1
    input  logic [31:0] b,      // operand 2
    input  logic [3:0]  op, // ALU control
    output logic [31:0] y,      // result
    output logic        zero    // y == 0 flag
);

    // ALU op encoding
    localparam ALU_ADD = 4'b0000;
    localparam ALU_SUB = 4'b0001;
    localparam ALU_AND = 4'b0010;
    localparam ALU_OR  = 4'b0011;
    localparam ALU_XOR = 4'b0100;
    localparam ALU_SLT = 4'b0101; // signed <
    localparam ALU_SLL = 4'b0110; // logical left shift
    localparam ALU_SRL = 4'b0111; // logical right shift
    localparam ALU_SRA = 4'b1000; // arithmetic right shift

    always_comb begin
        unique case (op)
            ALU_ADD: y = a + b;
            ALU_SUB: y = a - b;
            ALU_AND: y = a & b;
            ALU_OR:  y = a | b;
            ALU_XOR: y = a ^ b;
            ALU_SLT: y = ($signed(a) < $signed(b)) ? 32'd1 : 32'd0;
            ALU_SLL: y = a << b[4:0];
            ALU_SRL: y = a >> b[4:0];
            ALU_SRA: y = $signed(a) >>> b[4:0];
            default: y = 32'b0;
        endcase
    end

    assign zero = (y == 32'b0);

endmodule

tb/alu_tb.sv
module alu_tb;

    logic [31:0] a, b;
    logic [3:0]  op;
    logic [31:0] y;
    logic        zero;

    int tests = 0;
    int pass  = 0;

    // DUT
    alu dut (
        .a(a),
        .b(b),
        .op(op),
        .y(y),
        .zero(zero)
    );

    task check(input [31:0] exp);
        tests++;
        #1;
        if (y === exp) begin
            $display(" ✓ PASS: y = %0d", y);
            pass++;
        end else begin
            $display(" ✗ FAIL: expected %0d, got %0d", exp, y);
        end
    endtask

    initial begin
        $dumpfile("alu.vcd");
        $dumpvars(0, alu_tb);

        $display("\n=== ALU TESTS ===\n");

        // ADD
        $display("ADD");
        op = 4'b0000;
        a = 10; b = 20; check(30);

        // SUB
        $display("SUB");
        op = 4'b0001;
        a = 50; b = 20; check(30);

        // AND
        $display("AND");
        op = 4'b0010;
        a = 32'hF0F0; b = 32'h0FF0; check(32'h00F0);

        // OR
        $display("OR");
        op = 4'b0011;
        a = 32'hF0F0; b = 32'h0FF0; check(32'hFFF0);

        // XOR
        $display("XOR");
        op = 4'b0100;
        a = 32'hAAAA; b = 32'h5555; check(32'hFFFF);

        // SLT signed
        $display("SLT");
        op = 4'b0101;
        a = -5; b = 10; check(1);
        a = 10; b = -5; check(0);

        // SLL
        $display("SLL");
        op = 4'b0110;
        a = 1; b = 4; check(16);

        // SRL
        $display("SRL");
        op = 4'b0111;
        a = 32'h80000000; b = 1; check(32'h40000000);

        // Zero flag test
        $display("ZERO flag");
        op = 4'b0001;
        a = 10; b = 10;
        #1;
        if (zero) begin
            $display(" ✓ PASS: zero flag set");
            pass++;
        end else begin
            $display(" ✗ FAIL: zero flag not set");
        end
        tests++;

        $display("\n===============================");
        $display("Passed %0d / %0d tests", pass, tests);
        if (pass == tests) $display("Status: ✓ ALL TESTS PASSED");
        else $fatal(1, "Some tests failed");
        $display("===============================\n");

        #5 $finish;
    end

endmodule

alu.vcd
$version Generated by VerilatedVcd $end
$timescale 1ps $end
 $scope module TOP $end
  $scope module alu_tb $end
   $var wire 32 # a [31:0] $end
   $var wire 32 $ b [31:0] $end
   $var wire 4 % op [3:0] $end
   $var wire 32 & y [31:0] $end
   $var wire 1 ' zero $end
   $var wire 32 ( tests [31:0] $end
   $var wire 32 ) pass [31:0] $end
   $scope module dut $end
    $var wire 32 # a [31:0] $end
    $var wire 32 $ b [31:0] $end
    $var wire 4 % op [3:0] $end
    $var wire 32 & y [31:0] $end
    $var wire 1 ' zero $end
    $var wire 4 * ALU_ADD [3:0] $end
    $var wire 4 + ALU_SUB [3:0] $end
    $var wire 4 , ALU_AND [3:0] $end
    $var wire 4 - ALU_OR [3:0] $end
    $var wire 4 . ALU_XOR [3:0] $end
    $var wire 4 / ALU_SLT [3:0] $end
    $var wire 4 0 ALU_SLL [3:0] $end
    $var wire 4 1 ALU_SRL [3:0] $end
    $var wire 4 2 ALU_SRA [3:0] $end
   $upscope $end
  $upscope $end
 $upscope $end
$enddefinitions $end


#0
b00000000000000000000000000001010 #
b00000000000000000000000000010100 $
b0000 %
b00000000000000000000000000011110 &
0'
b00000000000000000000000000000001 (
b00000000000000000000000000000000 )
b0000 *
b0001 +
b0010 ,
b0011 -
b0100 .
b0101 /
b0110 0
b0111 1
b1000 2
#1
b00000000000000000000000000110010 #
b0001 %
b00000000000000000000000000000010 (
b00000000000000000000000000000001 )
#2
b00000000000000001111000011110000 #
b00000000000000000000111111110000 $
b0010 %
b00000000000000000000000011110000 &
b00000000000000000000000000000011 (
b00000000000000000000000000000010 )
#3
b0011 %
b00000000000000001111111111110000 &
b00000000000000000000000000000100 (
b00000000000000000000000000000011 )
#4
b00000000000000001010101010101010 #
b00000000000000000101010101010101 $
b0100 %
b00000000000000001111111111111111 &
b00000000000000000000000000000101 (
b00000000000000000000000000000100 )
#5
b11111111111111111111111111111011 #
b00000000000000000000000000001010 $
b0101 %
b00000000000000000000000000000001 &
b00000000000000000000000000000110 (
b00000000000000000000000000000101 )
#6
b00000000000000000000000000001010 #
b11111111111111111111111111111011 $
b00000000000000000000000000000000 &
1'
b00000000000000000000000000000111 (
b00000000000000000000000000000110 )
#7
b00000000000000000000000000000001 #
b00000000000000000000000000000100 $
b0110 %
b00000000000000000000000000010000 &
0'
b00000000000000000000000000001000 (
b00000000000000000000000000000111 )
#8
b10000000000000000000000000000000 #
b00000000000000000000000000000001 $
b0111 %
b01000000000000000000000000000000 &
b00000000000000000000000000001001 (
b00000000000000000000000000001000 )
#9
b00000000000000000000000000001010 #
b00000000000000000000000000001010 $
b0001 %
b00000000000000000000000000000000 &
1'
b00000000000000000000000000001001 )
#10
b00000000000000000000000000001010 (
b00000000000000000000000000001010 )
