rtl/alu.sv
module alu (
    input  logic [31:0] a,      // operand 1
    input  logic [31:0] b,      // operand 2
    input  logic [3:0]  op, // ALU control
    output logic [31:0] y,      // result
    output logic        zero    // y == 0 flag
);

    // ALU op encoding
    localparam ALU_ADD = 4'b0000;
    localparam ALU_SUB = 4'b0001;
    localparam ALU_AND = 4'b0010;
    localparam ALU_OR  = 4'b0011;
    localparam ALU_XOR = 4'b0100;
    localparam ALU_SLT = 4'b0101; // signed <
    localparam ALU_SLL = 4'b0110; // logical left shift
    localparam ALU_SRL = 4'b0111; // logical right shift
    localparam ALU_SRA = 4'b1000; // arithmetic right shift

    always_comb begin
        unique case (op)
            ALU_ADD: y = a + b;
            ALU_SUB: y = a - b;
            ALU_AND: y = a & b;
            ALU_OR:  y = a | b;
            ALU_XOR: y = a ^ b;
            ALU_SLT: y = ($signed(a) < $signed(b)) ? 32'd1 : 32'd0;
            ALU_SLL: y = a << b[4:0];
            ALU_SRL: y = a >> b[4:0];
            ALU_SRA: y = $signed(a) >>> b[4:0];
            default: y = 32'b0;
        endcase
    end

    assign zero = (y == 32'b0);

endmodule

rtl/register.sv
module register (
    input  logic        clk,
    input  logic        rst,
    input  logic        we,        // write enable
    input  logic [4:0]  rs1,       // source register 1
    input  logic [4:0]  rs2,       // source register 2
    input  logic [4:0]  rd,        // destination register
    input  logic [31:0] wd,        // write data

    output logic [31:0] rd1,       // read data 1
    output logic [31:0] rd2        // read data 2
);

    logic [31:0] regs [31:0];

    // Read ports (combinational)
    always_comb begin
        rd1 = (rs1 == 0) ? 32'b0 : regs[rs1];
        rd2 = (rs2 == 0) ? 32'b0 : regs[rs2];
    end

    // Write port (synchronous)
    always_ff @(posedge clk) begin
       if (rst) begin
            // Clear all registers on reset
            integer i;
            for (i = 0; i < 32; i = i + 1)
                regs[i] <= 32'b0;
        end else if (we && rd != 0)
            regs[rd] <= wd;
    end

endmodule

rtl/decoder.sv
module decoder (
    input  logic [31:0] instruction,
    output logic [6:0]  opcode,
    output logic [4:0]  rd,
    output logic [4:0]  rs1,
    output logic [4:0]  rs2,
    output logic [2:0]  funct3,
    output logic [6:0]  funct7,
    output logic [31:0] imm
);

    // Define RISC-V opcodes as an enum for readability
    typedef enum logic [6:0] {
        OP_LUI    = 7'b0110111,  // Load Upper Immediate
        OP_AUIPC  = 7'b0010111,  // Add Upper Immediate to PC
        OP_JAL    = 7'b1101111,  // Jump and Link
        OP_JALR   = 7'b1100111,  // Jump and Link Register
        OP_BRANCH = 7'b1100011,  // Branch instructions
        OP_LOAD   = 7'b0000011,  // Load instructions
        OP_STORE  = 7'b0100011,  // Store instructions
        OP_IMM    = 7'b0010011,  // Immediate arithmetic
        OP_REG    = 7'b0110011   // Register-register arithmetic
    } opcode_t;

    always_comb begin
        // Extract common fields
        opcode = instruction[6:0];
        rd     = instruction[11:7];
        funct3 = instruction[14:12];
        rs1    = instruction[19:15];
        rs2    = instruction[24:20];
        funct7 = instruction[31:25];
        
        // Decode immediate based on instruction type
        case (opcode)
            OP_IMM,    // I-type (ADDI, SLTI, XORI, etc.)
            OP_LOAD,   // I-type (LB, LH, LW, etc.)
            OP_JALR:   // I-type (JALR)
                // Sign-extend 12-bit immediate
                imm = {{20{instruction[31]}}, instruction[31:20]};
                
            OP_STORE:  // S-type (SB, SH, SW)
                // Sign-extend and reconstruct immediate
                imm = {{20{instruction[31]}}, instruction[31:25], instruction[11:7]};
                
            OP_BRANCH: // B-type (BEQ, BNE, BLT, etc.)
                // Sign-extend and reconstruct branch offset
                imm = {{19{instruction[31]}}, instruction[31], instruction[7], 
                       instruction[30:25], instruction[11:8], 1'b0};
                
            OP_LUI,    // U-type (LUI)
            OP_AUIPC:  // U-type (AUIPC)
                // Upper immediate (already shifted left by 12)
                imm = {instruction[31:12], 12'b0};
                
            OP_JAL:    // J-type (JAL)
                // Sign-extend and reconstruct jump offset
                imm = {{11{instruction[31]}}, instruction[31], instruction[19:12],
                       instruction[20], instruction[30:21], 1'b0};
                
            OP_REG:    // R-type (ADD, SUB, AND, OR, etc.)
                // R-type has no immediate field
                imm = 32'b0;
                
            default: 
                imm = 32'b0;
        endcase
    end

endmodule

rtl/cpu.sv
module cpu (
    input  logic clk,
    input  logic rst
);

    // -----------------------
    // Program Counter
    // -----------------------
    logic [31:0] pc;

    always_ff @(posedge clk or posedge rst) begin
        if (rst)
            pc <= 32'b0;
        else //index instruction address
            pc <= pc + 32'd4;
    end

    // -----------------------
    // Instruction Memory
    // -----------------------
    logic [31:0] imem [0:255];
    logic [31:0] instruction;

     // word aligned instruction store (bits 1:0 are junk), only need max size of 256
 
     assign instruction = imem[pc[9:2]]; 

    // -----------------------
    // Decode
    // -----------------------
    logic [6:0] opcode;
    logic [4:0] rd, rs1, rs2;
    logic [2:0] funct3;
    logic [6:0] funct7;
    logic [31:0] imm;

    decoder dec (
        .instruction(instruction),
        .opcode(opcode), //output
        .rd(rd), //output
        .rs1(rs1), //output
        .rs2(rs2), //output
        .funct3(funct3), //output
        .funct7(funct7), //output
        .imm(imm) //output
    );

    // -----------------------
    // Register File
    // -----------------------
    logic [31:0] rd1, rd2;

    register rf (
        .clk(clk),
        .rst(rst),
        .we(opcode == 7'b0110011), // R-type only
        .rs1(rs1),
        .rs2(rs2),
        .rd(rd),
        .wd(alu_y),
        .rd1(rd1), //output
        .rd2(rd2) //output
    );

    // -----------------------
    // ALU
    // -----------------------
    logic [31:0] alu_y;
    logic zero;

    alu alu0 (
        .a(rd1),
        .b(rd2),
        .op(4'b0000), // ADD only for now
        .y(alu_y),
        .zero(zero)
    );

    initial begin
        imem[0] = 32'h002081B3; // ADD x3, x1, x2
        imem[1] = 32'h00118233; // ADD x4, x3, x1
        imem[2] = 32'h00000013; // NOP
    end

endmodule

tb/cpu_tb.sv
module cpu_tb;

    logic clk = 0;
    logic rst = 1;

    cpu dut(.clk(clk), .rst(rst));

    always #5 clk = ~clk;

    initial begin
        $dumpfile("cpu.vcd");
        $dumpvars(0, cpu_tb);

        #10 rst = 0;

        // preload registers
        dut.rf.regs[1] = 10; // x1
        dut.rf.regs[2] = 20; // x2

        #50;

        $display("x3 = %0d", dut.rf.regs[3]); // expect 30
        $display("x4 = %0d", dut.rf.regs[4]); // expect 40

        $finish;
    end
endmodule

cpu.vcd
$version Generated by VerilatedVcd $end
$timescale 1ps $end
 $scope module TOP $end
  $scope module cpu_tb $end
   $var wire 1 L clk $end
   $var wire 1 M rst $end
   $scope module dut $end
    $var wire 1 L clk $end
    $var wire 1 M rst $end
    $var wire 32 N pc [31:0] $end
    $var wire 32 C instruction [31:0] $end
    $var wire 7 D opcode [6:0] $end
    $var wire 5 E rd [4:0] $end
    $var wire 5 F rs1 [4:0] $end
    $var wire 5 G rs2 [4:0] $end
    $var wire 3 H funct3 [2:0] $end
    $var wire 7 I funct7 [6:0] $end
    $var wire 32 J imm [31:0] $end
    $var wire 32 O rd1 [31:0] $end
    $var wire 32 P rd2 [31:0] $end
    $var wire 32 Q alu_y [31:0] $end
    $var wire 1 R zero $end
    $scope module alu0 $end
     $var wire 32 O a [31:0] $end
     $var wire 32 P b [31:0] $end
     $var wire 4 T op [3:0] $end
     $var wire 32 Q y [31:0] $end
     $var wire 1 R zero $end
     $var wire 4 T ALU_ADD [3:0] $end
     $var wire 4 U ALU_SUB [3:0] $end
     $var wire 4 V ALU_AND [3:0] $end
     $var wire 4 W ALU_OR [3:0] $end
     $var wire 4 X ALU_XOR [3:0] $end
     $var wire 4 Y ALU_SLT [3:0] $end
     $var wire 4 Z ALU_SLL [3:0] $end
     $var wire 4 [ ALU_SRL [3:0] $end
     $var wire 4 \ ALU_SRA [3:0] $end
    $upscope $end
    $scope module dec $end
     $var wire 32 C instruction [31:0] $end
     $var wire 7 D opcode [6:0] $end
     $var wire 5 E rd [4:0] $end
     $var wire 5 F rs1 [4:0] $end
     $var wire 5 G rs2 [4:0] $end
     $var wire 3 H funct3 [2:0] $end
     $var wire 7 I funct7 [6:0] $end
     $var wire 32 J imm [31:0] $end
    $upscope $end
    $scope module rf $end
     $var wire 1 L clk $end
     $var wire 1 M rst $end
     $var wire 1 K we $end
     $var wire 5 F rs1 [4:0] $end
     $var wire 5 G rs2 [4:0] $end
     $var wire 5 E rd [4:0] $end
     $var wire 32 Q wd [31:0] $end
     $var wire 32 O rd1 [31:0] $end
     $var wire 32 P rd2 [31:0] $end
     $var wire 32 # regs[0] [31:0] $end
     $var wire 32 $ regs[1] [31:0] $end
     $var wire 32 % regs[2] [31:0] $end
     $var wire 32 & regs[3] [31:0] $end
     $var wire 32 ' regs[4] [31:0] $end
     $var wire 32 ( regs[5] [31:0] $end
     $var wire 32 ) regs[6] [31:0] $end
     $var wire 32 * regs[7] [31:0] $end
     $var wire 32 + regs[8] [31:0] $end
     $var wire 32 , regs[9] [31:0] $end
     $var wire 32 - regs[10] [31:0] $end
     $var wire 32 . regs[11] [31:0] $end
     $var wire 32 / regs[12] [31:0] $end
     $var wire 32 0 regs[13] [31:0] $end
     $var wire 32 1 regs[14] [31:0] $end
     $var wire 32 2 regs[15] [31:0] $end
     $var wire 32 3 regs[16] [31:0] $end
     $var wire 32 4 regs[17] [31:0] $end
     $var wire 32 5 regs[18] [31:0] $end
     $var wire 32 6 regs[19] [31:0] $end
     $var wire 32 7 regs[20] [31:0] $end
     $var wire 32 8 regs[21] [31:0] $end
     $var wire 32 9 regs[22] [31:0] $end
     $var wire 32 : regs[23] [31:0] $end
     $var wire 32 ; regs[24] [31:0] $end
     $var wire 32 < regs[25] [31:0] $end
     $var wire 32 = regs[26] [31:0] $end
     $var wire 32 > regs[27] [31:0] $end
     $var wire 32 ? regs[28] [31:0] $end
     $var wire 32 @ regs[29] [31:0] $end
     $var wire 32 A regs[30] [31:0] $end
     $var wire 32 B regs[31] [31:0] $end
     $scope module unnamedblk1 $end
      $var wire 32 S i [31:0] $end
     $upscope $end
    $upscope $end
   $upscope $end
  $upscope $end
 $upscope $end
$enddefinitions $end


#0
b00000000000000000000000000000000 #
b00000000000000000000000000000000 $
b00000000000000000000000000000000 %
b00000000000000000000000000000000 &
b00000000000000000000000000000000 '
b00000000000000000000000000000000 (
b00000000000000000000000000000000 )
b00000000000000000000000000000000 *
b00000000000000000000000000000000 +
b00000000000000000000000000000000 ,
b00000000000000000000000000000000 -
b00000000000000000000000000000000 .
b00000000000000000000000000000000 /
b00000000000000000000000000000000 0
b00000000000000000000000000000000 1
b00000000000000000000000000000000 2
b00000000000000000000000000000000 3
b00000000000000000000000000000000 4
b00000000000000000000000000000000 5
b00000000000000000000000000000000 6
b00000000000000000000000000000000 7
b00000000000000000000000000000000 8
b00000000000000000000000000000000 9
b00000000000000000000000000000000 :
b00000000000000000000000000000000 ;
b00000000000000000000000000000000 <
b00000000000000000000000000000000 =
b00000000000000000000000000000000 >
b00000000000000000000000000000000 ?
b00000000000000000000000000000000 @
b00000000000000000000000000000000 A
b00000000000000000000000000000000 B
b00000000001000001000000110110011 C
b0110011 D
b00011 E
b00001 F
b00010 G
b000 H
b0000000 I
b00000000000000000000000000000000 J
1K
0L
1M
b00000000000000000000000000000000 N
b00000000000000000000000000000000 O
b00000000000000000000000000000000 P
b00000000000000000000000000000000 Q
1R
b00000000000000000000000000000000 S
b0000 T
b0001 U
b0010 V
b0011 W
b0100 X
b0101 Y
b0110 Z
b0111 [
b1000 \
#5
1L
b00000000000000000000000000100000 S
#10
b00000000000000000000000000001010 $
b00000000000000000000000000010100 %
0L
0M
b00000000000000000000000000001010 O
b00000000000000000000000000010100 P
b00000000000000000000000000011110 Q
0R
#15
b00000000000100011000001000110011 C
b00100 E
b00011 F
b00001 G
1L
b00000000000000000000000000000100 N
b00000000000000000000000000000000 O
b00000000000000000000000000001010 P
b00000000000000000000000000001010 Q
#20
0L
#25
b00000000000000000000000000001010 '
b00000000000000000000000000010011 C
b0010011 D
b00000 E
b00000 F
b00000 G
0K
1L
b00000000000000000000000000001000 N
b00000000000000000000000000000000 P
b00000000000000000000000000000000 Q
1R
#30
0L
#35
b00000000000000000000000000000000 C
b0000000 D
1L
b00000000000000000000000000001100 N
#40
0L
#45
1L
b00000000000000000000000000010000 N
#50
0L
#55
1L
b00000000000000000000000000010100 N
