rtl/decoder.sv
module decoder (
    input  logic [31:0] instruction,
    output logic [6:0]  opcode,
    output logic [4:0]  rd,
    output logic [4:0]  rs1,
    output logic [4:0]  rs2,
    output logic [2:0]  funct3,
    output logic [6:0]  funct7,
    output logic [31:0] imm
);

    // Define RISC-V opcodes as an enum for readability
    typedef enum logic [6:0] {
        OP_LUI    = 7'b0110111,  // Load Upper Immediate
        OP_AUIPC  = 7'b0010111,  // Add Upper Immediate to PC
        OP_JAL    = 7'b1101111,  // Jump and Link
        OP_JALR   = 7'b1100111,  // Jump and Link Register
        OP_BRANCH = 7'b1100011,  // Branch instructions
        OP_LOAD   = 7'b0000011,  // Load instructions
        OP_STORE  = 7'b0100011,  // Store instructions
        OP_IMM    = 7'b0010011,  // Immediate arithmetic
        OP_REG    = 7'b0110011   // Register-register arithmetic
    } opcode_t;

    always_comb begin
        // Extract common fields
        opcode = instruction[6:0];
        rd     = instruction[11:7];
        funct3 = instruction[14:12];
        rs1    = instruction[19:15];
        rs2    = instruction[24:20];
        funct7 = instruction[31:25];
        
        // Decode immediate based on instruction type
        case (opcode)
            OP_IMM,    // I-type (ADDI, SLTI, XORI, etc.)
            OP_LOAD,   // I-type (LB, LH, LW, etc.)
            OP_JALR:   // I-type (JALR)
                // Sign-extend 12-bit immediate
                imm = {{20{instruction[31]}}, instruction[31:20]};
                
            OP_STORE:  // S-type (SB, SH, SW)
                // Sign-extend and reconstruct immediate
                imm = {{20{instruction[31]}}, instruction[31:25], instruction[11:7]};
                
            OP_BRANCH: // B-type (BEQ, BNE, BLT, etc.)
                // Sign-extend and reconstruct branch offset
                imm = {{19{instruction[31]}}, instruction[31], instruction[7], 
                       instruction[30:25], instruction[11:8], 1'b0};
                
            OP_LUI,    // U-type (LUI)
            OP_AUIPC:  // U-type (AUIPC)
                // Upper immediate (already shifted left by 12)
                imm = {instruction[31:12], 12'b0};
                
            OP_JAL:    // J-type (JAL)
                // Sign-extend and reconstruct jump offset
                imm = {{11{instruction[31]}}, instruction[31], instruction[19:12],
                       instruction[20], instruction[30:21], 1'b0};
                
            OP_REG:    // R-type (ADD, SUB, AND, OR, etc.)
                // R-type has no immediate field
                imm = 32'b0;
                
            default: 
                imm = 32'b0;
        endcase
    end

endmodule

tb/decoder_tb.sv
module decoder_tb;
    logic [31:0] instruction;
    logic [6:0]  opcode;
    logic [4:0]  rd, rs1, rs2;
    logic [2:0]  funct3;
    logic [6:0]  funct7;
    logic [31:0] imm;
    
    localparam int TOTAL_TESTS = 12;
    int tests_passed = 0;
    int local_checks;

    // DUT
    decoder dut (
        .instruction(instruction),
        .opcode(opcode),
        .rd(rd),
        .rs1(rs1),
        .rs2(rs2),
        .funct3(funct3),
        .funct7(funct7),
        .imm(imm)
    );

    // helper task (module scope)
    task reset_instr;
        begin
            instruction = 32'b0;
            #1;
        end
    endtask

    initial begin
        $dumpfile("decoder.vcd");
        $dumpvars(0, decoder_tb);
        $display("\n=== RISC-V Decoder Test ===\n");

        // ---------- Test 1 ----------
       // reset_instr(); 
        local_checks = 0;
        $display("Test 1: ADDI x1, x0, 10");
        instruction = 32'h00A00093; #10;
        if (opcode===7'b0010011) local_checks++;
        if (rd===1) local_checks++;
        if (rs1===0) local_checks++;
        if ($signed(imm)===10) local_checks++;
        if (local_checks==4) begin $display("  ✓ PASS\n"); tests_passed++; end else $display("  ✗ FAIL\n");

        // ---------- Test 2 ----------
       // reset_instr();
        local_checks = 0;
        $display("Test 2: ADD x3, x1, x2");
        instruction = 32'h002081B3; #10;
        if (opcode===7'b0110011) local_checks++;
        if (rd===3) local_checks++;
        if (rs1===1) local_checks++;
        if (rs2===2) local_checks++;
        if (funct3===3'b000) local_checks++;
        if (funct7===7'b0000000) local_checks++;
        if (local_checks==6) begin $display("  ✓ PASS\n"); tests_passed++; end else $display("  ✗ FAIL\n");

        // ---------- Test 3 ----------
        //reset_instr();
         local_checks = 0;
        $display("Test 3: BEQ x1, x2, 8");
        instruction = 32'h00208463; #10;
        if (opcode===7'b1100011) local_checks++;
        if (rs1===1) local_checks++;
        if (rs2===2) local_checks++;
        if ($signed(imm)===8) local_checks++;
        if (local_checks==4) begin $display("  ✓ PASS\n"); tests_passed++; end else $display("  ✗ FAIL\n");

        // ---------- Test 4 ----------
        //reset_instr();
        local_checks = 0;
        $display("Test 4: LUI x5, 0x12345");
        instruction = 32'h123452B7; #10;
        if (opcode===7'b0110111) local_checks++;
        if (rd===5) local_checks++;
        if (imm===32'h12345000) local_checks++;
        if (local_checks==3) begin $display("  ✓ PASS\n"); tests_passed++; end else $display("  ✗ FAIL\n");

        // ---------- Test 5 ----------
       // reset_instr(); 
        local_checks = 0;
        $display("Test 5: JAL x1, 100");
        instruction = 32'h064000EF; #10;
        if (opcode===7'b1101111) local_checks++;
        if (rd===1) local_checks++;
        if ($signed(imm)===100) local_checks++;
        if (local_checks==3) begin $display("  ✓ PASS\n"); tests_passed++; end else $display("  ✗ FAIL\n");

        // ---------- Test 6 ----------
       // reset_instr();
        local_checks = 0;
        $display("Test 6: SW x2, 4(x1)");
        instruction = 32'h0020A223; #10;
        if (opcode===7'b0100011) local_checks++;
        if (rs1===1) local_checks++;
        if (rs2===2) local_checks++;
        if ($signed(imm)===4) local_checks++;
        if (local_checks==4) begin $display("  ✓ PASS\n"); tests_passed++; end else $display("  ✗ FAIL\n");

        // ---------- Test 7 ----------
       // reset_instr();
        local_checks = 0;
        $display("Test 7: ADDI x3, x0, -1");
        instruction = 32'hFFF00193; #10;
        if (opcode===7'b0010011) local_checks++;
        if (rd===3) local_checks++;
        if ($signed(imm)===-1) local_checks++;
        if (local_checks==3) begin $display("  ✓ PASS\n"); tests_passed++; end else $display("  ✗ FAIL\n");

        // ---------- Test 8 ----------
       // reset_instr();
        local_checks = 0;
        $display("Test 8: BEQ x0, x0, -4");
        instruction = 32'hFE000CE3; #10;
        if (opcode===7'b1100011) local_checks++;
        if ($signed(imm)===-4) local_checks++;
        if (local_checks==2) begin $display("  ✓ PASS\n"); tests_passed++; end else $display("  ✗ FAIL\n");

        // ---------- Test 9 ----------
       // reset_instr();
        local_checks = 0;
        $display("Test 9: JALR x1, 0(x2)");
        instruction = 32'h000100E7; #10;
        if (opcode===7'b1100111) local_checks++;
        if (rd===1) local_checks++;
        if (rs1===2) local_checks++;
        if ($signed(imm)===0) local_checks++;
        if (local_checks==4) begin $display("  ✓ PASS\n"); tests_passed++; end else $display("  ✗ FAIL\n");

        // ---------- Test 10 ----------
       // reset_instr();
        local_checks = 0;
        $display("Test 10: SLLI x4, x1, 3");
        instruction = 32'h00309213; #10;
        if (opcode===7'b0010011) local_checks++;
        if (rd===4) local_checks++;
        if (funct3===3'b001) local_checks++;
        if (imm[4:0]===3) local_checks++;
        if (local_checks==4) begin $display("  ✓ PASS\n"); tests_passed++; end else $display("  ✗ FAIL\n");

        // ---------- Test 11 ----------
       // reset_instr();
        local_checks = 0;
        $display("Test 11: SLTI x6, x1, 7");
        instruction = 32'h0070A313; #10;
        if (opcode===7'b0010011) local_checks++;
        if (rd===6) local_checks++;
        if (funct3===3'b010) local_checks++;
        if (imm===7) local_checks++;
        if (local_checks==4) begin $display("  ✓ PASS\n"); tests_passed++; end else $display("  ✗ FAIL\n");

        // ---------- Test 12 ----------
       // reset_instr();
        local_checks = 0;
        $display("Test 12: LB x3, 1(x2)");
        instruction = 32'h00110183; #10;
        if (opcode===7'b0000011) local_checks++;
        if (rd===3) local_checks++;
        if (rs1===2) local_checks++;
        if (funct3===3'b000) local_checks++;
        if (imm===1) local_checks++;
        if (local_checks==5) begin $display("  ✓ PASS\n"); tests_passed++; end else $display("  ✗ FAIL\n");

        // ---------- Summary ----------
        $display("================================");
        $display("Tests passed: %0d/%0d", tests_passed, TOTAL_TESTS);
        if (tests_passed == TOTAL_TESTS)
            $display("Status: ✓ ALL TESTS PASSED");
        else
            $fatal(1, "✗ SOME TESTS FAILED");
        $display("================================\n");

        #10 $finish;
    end
endmodule

decoder.vcd
$version Generated by VerilatedVcd $end
$timescale 1ps $end
 $scope module TOP $end
  $scope module decoder_tb $end
   $var wire 32 # instruction [31:0] $end
   $var wire 7 + opcode [6:0] $end
   $var wire 5 $ rd [4:0] $end
   $var wire 5 % rs1 [4:0] $end
   $var wire 5 & rs2 [4:0] $end
   $var wire 3 ' funct3 [2:0] $end
   $var wire 7 ( funct7 [6:0] $end
   $var wire 32 , imm [31:0] $end
   $var wire 32 - TOTAL_TESTS [31:0] $end
   $var wire 32 ) tests_passed [31:0] $end
   $var wire 32 * local_checks [31:0] $end
   $scope module dut $end
    $var wire 32 # instruction [31:0] $end
    $var wire 7 + opcode [6:0] $end
    $var wire 5 $ rd [4:0] $end
    $var wire 5 % rs1 [4:0] $end
    $var wire 5 & rs2 [4:0] $end
    $var wire 3 ' funct3 [2:0] $end
    $var wire 7 ( funct7 [6:0] $end
    $var wire 32 , imm [31:0] $end
   $upscope $end
  $upscope $end
 $upscope $end
$enddefinitions $end


#0
b00000000101000000000000010010011 #
b00001 $
b00000 %
b01010 &
b000 '
b0000000 (
b00000000000000000000000000000000 )
b00000000000000000000000000000000 *
b0010011 +
b00000000000000000000000000001010 ,
b00000000000000000000000000001100 -
#10
b00000000001000001000000110110011 #
b00011 $
b00001 %
b00010 &
b00000000000000000000000000000001 )
b0110011 +
b00000000000000000000000000000000 ,
#20
b00000000001000001000010001100011 #
b01000 $
b00000000000000000000000000000010 )
b1100011 +
b00000000000000000000000000001000 ,
#30
b00010010001101000101001010110111 #
b00101 $
b01000 %
b00011 &
b101 '
b0001001 (
b00000000000000000000000000000011 )
b0110111 +
b00010010001101000101000000000000 ,
#40
b00000110010000000000000011101111 #
b00001 $
b00000 %
b00100 &
b000 '
b0000011 (
b00000000000000000000000000000100 )
b1101111 +
b00000000000000000000000001100100 ,
#50
b00000000001000001010001000100011 #
b00100 $
b00001 %
b00010 &
b010 '
b0000000 (
b00000000000000000000000000000101 )
b0100011 +
b00000000000000000000000000000100 ,
#60
b11111111111100000000000110010011 #
b00011 $
b00000 %
b11111 &
b000 '
b1111111 (
b00000000000000000000000000000110 )
b0010011 +
b11111111111111111111111111111111 ,
#70
b11111110000000000000110011100011 #
b11001 $
b00000 &
b00000000000000000000000000000111 )
b1100011 +
b11111111111111111111111111111000 ,
#80
b00000000000000010000000011100111 #
b00001 $
b00010 %
b0000000 (
b1100111 +
b00000000000000000000000000000000 ,
#90
b00000000001100001001001000010011 #
b00100 $
b00001 %
b00011 &
b001 '
b00000000000000000000000000001000 )
b0010011 +
b00000000000000000000000000000011 ,
#100
b00000000011100001010001100010011 #
b00110 $
b00111 &
b010 '
b00000000000000000000000000001001 )
b00000000000000000000000000000111 ,
#110
b00000000000100010000000110000011 #
b00011 $
b00010 %
b00001 &
b000 '
b00000000000000000000000000001010 )
b0000011 +
b00000000000000000000000000000001 ,
