rtl/register.sv
module register (
    input  logic        clk,
    input  logic        rst,
    input  logic        we,        // write enable
    input  logic [4:0]  rs1,       // source register 1
    input  logic [4:0]  rs2,       // source register 2
    input  logic [4:0]  rd,        // destination register
    input  logic [31:0] wd,        // write data

    output logic [31:0] rd1,       // read data 1
    output logic [31:0] rd2        // read data 2
);

    logic [31:0] regs [31:0];

    // Read ports (combinational)
    always_comb begin
        rd1 = (rs1 == 0) ? 32'b0 : regs[rs1];
        rd2 = (rs2 == 0) ? 32'b0 : regs[rs2];
    end

    // Write port (synchronous)
    always_ff @(posedge clk) begin
       if (rst) begin
            // Clear all registers on reset
            integer i;
            for (i = 0; i < 32; i = i + 1)
                regs[i] <= 32'b0;
        end else if (we && rd != 0)
            regs[rd] <= wd;
    end

endmodule

tb/register_tb.sv
module register_tb;

    logic clk;
    logic rst;

    logic we;
    logic [4:0] rs1, rs2, rd;
    logic [31:0] wd;
    logic [31:0] rd1, rd2;

    localparam int TOTAL_TESTS = 8;
    int tests_passed = 0;

    // DUT
    register dut (
        .clk(clk),
        .rst(rst),
        .we(we),
        .rs1(rs1),
        .rs2(rs2),
        .rd(rd),
        .wd(wd),
        .rd1(rd1),
        .rd2(rd2)
    );

    // Clock
    always #5 clk = ~clk;

    initial begin
        clk = 0;
        rst = 1;
        we  = 0;
        rs1 = 0;
        rs2 = 0;
        rd  = 0;
        wd  = 0;

        $dumpfile("register.vcd");
        $dumpvars(0, register);

        $display("\n=== Register File Test ===\n");

        #10 rst = 0;

        // Test 1: x0 always 0
        begin
            automatic int ok = 0;
            $display("Test 1: x0 is always zero");
            rs1 = 0;
            #1;
            if (rd1 === 0) ok++; else $display(" ✗ x0 != 0 (%h)", rd1);
            if (ok == 1) begin $display(" ✓ PASS\n"); tests_passed++; end
            else $display(" ✗ FAIL\n");
        end

        // Test 2: Write x1 = 10
        begin
            automatic int ok = 0;
            $display("Test 2: Write x1 = 10");
            @(posedge clk);
            rd = 1; wd = 10; we = 1;
            @(posedge clk);
            we = 0;
            rs1 = 1; #1;
            if (rd1 === 10) ok++; else $display(" ✗ Expected 10, got %0d", rd1);
            if (ok == 1) begin $display(" ✓ PASS\n"); tests_passed++; end
            else $display(" ✗ FAIL\n");
        end

        // Test 3: Write x2 = 20
        begin
            automatic int ok = 0;
            $display("Test 3: Write x2 = 20");
            @(posedge clk);
            rd = 2; wd = 20; we = 1;
            @(posedge clk);
            we = 0;
            rs1 = 2; #1;
            if (rd1 === 20) ok++; else $display(" ✗ Expected 20, got %0d", rd1);
            if (ok == 1) begin $display(" ✓ PASS\n"); tests_passed++; end
            else $display(" ✗ FAIL\n");
        end

        // Test 4: Read two registers
        begin
            automatic int ok = 0;
            $display("Test 4: Read x1 and x2 together");
            @(posedge clk);
            rs1 = 1; rs2 = 2; #1;
            if (rd1 === 10) ok++; else $display(" ✗ x1 wrong");
            if (rd2 === 20) ok++; else $display(" ✗ x2 wrong");
            if (ok == 2) begin $display(" ✓ PASS\n"); tests_passed++; end
            else $display(" ✗ FAIL\n");
        end

        // Test 5: Overwrite x1
        begin
            automatic int ok = 0;
            $display("Test 5: Overwrite x1 = 99");
            @(posedge clk);
            rd = 1; wd = 99; we = 1;
            @(posedge clk);
            we = 0;
            rs1 = 1; #1;
            if (rd1 === 99) ok++; else $display(" ✗ Expected 99, got %0d", rd1);
            if (ok == 1) begin $display(" ✓ PASS\n"); tests_passed++; end
            else $display(" ✗ FAIL\n");
        end

        // Test 6: Attempt write to x0
        begin
            automatic int ok = 0;
            $display("Test 6: Write to x0 ignored");
            @(posedge clk);
            rd = 0; wd = 1234; we = 1;
            @(posedge clk);
            we = 0;
            rs1 = 0; #1;
            if (rd1 === 0) ok++; else $display(" ✗ x0 changed!");
            if (ok == 1) begin $display(" ✓ PASS\n"); tests_passed++; end
            else $display(" ✗ FAIL\n");
        end

        // Test 7: Read & write same reg same cycle
        begin
            automatic int ok = 0;
            $display("Test 7: Read and write x3 same cycle");
            @(posedge clk);
            rd = 3; wd = 55; we = 1;
            rs1 = 3;
            @(posedge clk);
            we = 0;
            #1;
            if (rd1 === 55) ok++; else $display(" ✗ Expected 55, got %0d", rd1);
            if (ok == 1) begin $display(" ✓ PASS\n"); tests_passed++; end
            else $display(" ✗ FAIL\n");
        end

        // Test 8: Reset clears regs
        begin
            automatic int ok = 0;
            $display("Test 8: Reset clears registers");
            @(posedge clk);
            rst = 1; @(posedge clk); rst = 0;
            rs1 = 1; #1;
            if (rd1 === 0) ok++; else $display(" ✗ x1 not cleared");
            if (ok == 1) begin $display(" ✓ PASS\n"); tests_passed++; end
            else $display(" ✗ FAIL\n");
        end

        $display("================================");
        $display("Tests passed: %0d/%0d", tests_passed, TOTAL_TESTS);
        if (tests_passed == TOTAL_TESTS)
            $display("Status: ✓ ALL TESTS PASSED");
        else
            $display( "Some tests failed");
        $display("================================\n");

        #10 $finish;
    end
endmodule

register.vcd
$version Generated by VerilatedVcd $end
$timescale 1ps $end
 $scope module TOP $end
  $scope module register_tb $end
   $var wire 1 S clk $end
   $var wire 1 # rst $end
   $var wire 1 $ we $end
   $var wire 5 % rs1 [4:0] $end
   $var wire 5 & rs2 [4:0] $end
   $var wire 5 ' rd [4:0] $end
   $var wire 32 ( wd [31:0] $end
   $var wire 32 T rd1 [31:0] $end
   $var wire 32 U rd2 [31:0] $end
   $var wire 32 V TOTAL_TESTS [31:0] $end
   $var wire 32 ) tests_passed [31:0] $end
   $scope module dut $end
    $var wire 1 S clk $end
    $var wire 1 # rst $end
    $var wire 1 $ we $end
    $var wire 5 % rs1 [4:0] $end
    $var wire 5 & rs2 [4:0] $end
    $var wire 5 ' rd [4:0] $end
    $var wire 32 ( wd [31:0] $end
    $var wire 32 T rd1 [31:0] $end
    $var wire 32 U rd2 [31:0] $end
    $var wire 32 2 regs[0] [31:0] $end
    $var wire 32 3 regs[1] [31:0] $end
    $var wire 32 4 regs[2] [31:0] $end
    $var wire 32 5 regs[3] [31:0] $end
    $var wire 32 6 regs[4] [31:0] $end
    $var wire 32 7 regs[5] [31:0] $end
    $var wire 32 8 regs[6] [31:0] $end
    $var wire 32 9 regs[7] [31:0] $end
    $var wire 32 : regs[8] [31:0] $end
    $var wire 32 ; regs[9] [31:0] $end
    $var wire 32 < regs[10] [31:0] $end
    $var wire 32 = regs[11] [31:0] $end
    $var wire 32 > regs[12] [31:0] $end
    $var wire 32 ? regs[13] [31:0] $end
    $var wire 32 @ regs[14] [31:0] $end
    $var wire 32 A regs[15] [31:0] $end
    $var wire 32 B regs[16] [31:0] $end
    $var wire 32 C regs[17] [31:0] $end
    $var wire 32 D regs[18] [31:0] $end
    $var wire 32 E regs[19] [31:0] $end
    $var wire 32 F regs[20] [31:0] $end
    $var wire 32 G regs[21] [31:0] $end
    $var wire 32 H regs[22] [31:0] $end
    $var wire 32 I regs[23] [31:0] $end
    $var wire 32 J regs[24] [31:0] $end
    $var wire 32 K regs[25] [31:0] $end
    $var wire 32 L regs[26] [31:0] $end
    $var wire 32 M regs[27] [31:0] $end
    $var wire 32 N regs[28] [31:0] $end
    $var wire 32 O regs[29] [31:0] $end
    $var wire 32 P regs[30] [31:0] $end
    $var wire 32 Q regs[31] [31:0] $end
    $scope module unnamedblk1 $end
     $var wire 32 R i [31:0] $end
    $upscope $end
   $upscope $end
   $scope module unnamedblk1 $end
    $var wire 32 * ok [31:0] $end
   $upscope $end
   $scope module unnamedblk2 $end
    $var wire 32 + ok [31:0] $end
   $upscope $end
   $scope module unnamedblk3 $end
    $var wire 32 , ok [31:0] $end
   $upscope $end
   $scope module unnamedblk4 $end
    $var wire 32 - ok [31:0] $end
   $upscope $end
   $scope module unnamedblk5 $end
    $var wire 32 . ok [31:0] $end
   $upscope $end
   $scope module unnamedblk6 $end
    $var wire 32 / ok [31:0] $end
   $upscope $end
   $scope module unnamedblk7 $end
    $var wire 32 0 ok [31:0] $end
   $upscope $end
   $scope module unnamedblk8 $end
    $var wire 32 1 ok [31:0] $end
   $upscope $end
  $upscope $end
 $upscope $end
$enddefinitions $end


#0
1#
0$
b00000 %
b00000 &
b00000 '
b00000000000000000000000000000000 (
b00000000000000000000000000000000 )
b00000000000000000000000000000000 *
b00000000000000000000000000000000 +
b00000000000000000000000000000000 ,
b00000000000000000000000000000000 -
b00000000000000000000000000000000 .
b00000000000000000000000000000000 /
b00000000000000000000000000000000 0
b00000000000000000000000000000000 1
b00000000000000000000000000000000 2
b00000000000000000000000000000000 3
b00000000000000000000000000000000 4
b00000000000000000000000000000000 5
b00000000000000000000000000000000 6
b00000000000000000000000000000000 7
b00000000000000000000000000000000 8
b00000000000000000000000000000000 9
b00000000000000000000000000000000 :
b00000000000000000000000000000000 ;
b00000000000000000000000000000000 <
b00000000000000000000000000000000 =
b00000000000000000000000000000000 >
b00000000000000000000000000000000 ?
b00000000000000000000000000000000 @
b00000000000000000000000000000000 A
b00000000000000000000000000000000 B
b00000000000000000000000000000000 C
b00000000000000000000000000000000 D
b00000000000000000000000000000000 E
b00000000000000000000000000000000 F
b00000000000000000000000000000000 G
b00000000000000000000000000000000 H
b00000000000000000000000000000000 I
b00000000000000000000000000000000 J
b00000000000000000000000000000000 K
b00000000000000000000000000000000 L
b00000000000000000000000000000000 M
b00000000000000000000000000000000 N
b00000000000000000000000000000000 O
b00000000000000000000000000000000 P
b00000000000000000000000000000000 Q
b00000000000000000000000000000000 R
0S
b00000000000000000000000000000000 T
b00000000000000000000000000000000 U
b00000000000000000000000000001000 V
#5
b00000000000000000000000000100000 R
1S
#10
0#
0S
#11
b00000000000000000000000000000001 )
b00000000000000000000000000000001 *
#15
1$
b00001 '
b00000000000000000000000000001010 (
b00000000000000000000000000001010 3
1S
#20
0S
#25
0$
b00001 %
1S
b00000000000000000000000000001010 T
#26
b00000000000000000000000000000010 )
b00000000000000000000000000000001 +
#30
0S
#35
1$
b00010 '
b00000000000000000000000000010100 (
b00000000000000000000000000010100 4
1S
#40
0S
#45
0$
b00010 %
1S
b00000000000000000000000000010100 T
#46
b00000000000000000000000000000011 )
b00000000000000000000000000000001 ,
#50
0S
#55
b00001 %
b00010 &
1S
b00000000000000000000000000001010 T
b00000000000000000000000000010100 U
#56
b00000000000000000000000000000100 )
b00000000000000000000000000000010 -
#60
0S
#65
1$
b00001 '
b00000000000000000000000001100011 (
b00000000000000000000000001100011 3
1S
b00000000000000000000000001100011 T
#70
0S
#75
0$
1S
#76
b00000000000000000000000000000101 )
b00000000000000000000000000000001 .
#80
0S
#85
1$
b00000 '
b00000000000000000000010011010010 (
1S
#90
0S
#95
0$
b00000 %
1S
b00000000000000000000000000000000 T
#96
b00000000000000000000000000000110 )
b00000000000000000000000000000001 /
#100
0S
#105
1$
b00011 %
b00011 '
b00000000000000000000000000110111 (
b00000000000000000000000000110111 5
1S
b00000000000000000000000000110111 T
#110
0S
#115
0$
1S
#116
b00000000000000000000000000000111 )
b00000000000000000000000000000001 0
#120
0S
#125
1#
b00000000000000000000000000000000 3
b00000000000000000000000000000000 4
b00000000000000000000000000000000 5
1S
b00000000000000000000000000000000 T
b00000000000000000000000000000000 U
#130
0S
#135
0#
b00001 %
1S
#136
b00000000000000000000000000001000 )
b00000000000000000000000000000001 1
